MANIFEST.in
README.txt
setup.cfg
setup.py
docs/HISTORY.txt
docs/LICENSE.txt
raptus/__init__.py
raptus.multilanguageplone.egg-info/PKG-INFO
raptus.multilanguageplone.egg-info/SOURCES.txt
raptus.multilanguageplone.egg-info/dependency_links.txt
raptus.multilanguageplone.egg-info/entry_points.txt
raptus.multilanguageplone.egg-info/namespace_packages.txt
raptus.multilanguageplone.egg-info/not-zip-safe
raptus.multilanguageplone.egg-info/requires.txt
raptus.multilanguageplone.egg-info/top_level.txt
raptus/multilanguageplone/README.txt
raptus/multilanguageplone/__init__.py
raptus/multilanguageplone/configure.zcml
raptus/multilanguageplone/setuphandlers.py
raptus/multilanguageplone/Extensions/Install.py
raptus/multilanguageplone/Extensions/__init__.py
raptus/multilanguageplone/extender/__init__.py
raptus/multilanguageplone/extender/base.py
raptus/multilanguageplone/extender/document.py
raptus/multilanguageplone/extender/event.py
raptus/multilanguageplone/extender/fields.py
raptus/multilanguageplone/extender/file.py
raptus/multilanguageplone/extender/folder.py
raptus/multilanguageplone/extender/image.py
raptus/multilanguageplone/extender/link.py
raptus/multilanguageplone/extender/newsitem.py
raptus/multilanguageplone/extender/topic.py
raptus/multilanguageplone/profiles/default/metadata.xml
raptus/multilanguageplone/profiles/default/portal_languages.xml
raptus/multilanguageplone/profiles/default/raptus.multilanguageplone_install.txt
raptus/multilanguageplone/profiles/uninstall/import_steps.xml
raptus/multilanguageplone/profiles/uninstall/metadata.xml
raptus/multilanguageplone/profiles/uninstall/raptus.multilanguageplone_uninstall.txt
raptus/multilanguageplone/tests/__init__.py
raptus/multilanguageplone/tests/base.py
raptus/multilanguageplone/tests/test_doctest.py