Metadata-Version: 1.0
Name: raptus.multilanguageplone
Version: 1.0
Summary: adding multilanguage support to default plone content types
Home-page: http://plone.org/products/raptus.multilanguageplone
Author: Raptus AG
Author-email: dev@raptus.com
License: GPL
Platform: UNKNOWN
Classifier: Programming Language :: Python
Classifier: Topic :: Software Development :: Libraries :: Python Modules
Classifier: License :: OSI Approved :: GNU General Public License (GPL)
